foxtrot/__init__.py
foxtrot/_modidx.py
foxtrot/core.py
foxtrot_beta-0.0.3.dist-info/LICENSE
foxtrot_beta-0.0.3.dist-info/METADATA
foxtrot_beta-0.0.3.dist-info/WHEEL
foxtrot_beta-0.0.3.dist-info/entry_points.txt
foxtrot_beta-0.0.3.dist-info/top_level.txt
foxtrot_beta-0.0.3.dist-info/RECORD
