Metadata-Version: 2.1
Name: foxtrot-beta
Version: 0.0.3
Summary: like boxstep, but fancier
Home-page: https://licenseplated.github.io/foxtrot
Author: licenseplated
Author-email: martinezah@gmail.com
License: Apache Software License 2.0
Keywords: nbdev jupyter notebook python
Platform: UNKNOWN
Classifier: Development Status :: 4 - Beta
Classifier: Intended Audience :: Developers
Classifier: Natural Language :: English
Classifier: Programming Language :: Python :: 3.7
Classifier: Programming Language :: Python :: 3.8
Classifier: Programming Language :: Python :: 3.9
Classifier: Programming Language :: Python :: 3.10
Classifier: License :: OSI Approved :: Apache Software License
Requires-Python: >=3.7
License-File: LICENSE
Requires-Dist: transitions
Provides-Extra: dev
